[
  {
    "eposideId": 0,
    "goal": {
      "position": {
        "x": 0.6347665952348857,
        "y": -0.2482608464615284
      },
      "rotation": {
        "theta": 0.544719687238046
      }
    },
    "finalPose": {
      "position": {
        "x": 0.6718483143235885,
        "y": -0.23452121868326742
      },
      "rotation": {
        "theta": 0.5336689388195219
      }
    },
    "error": {
      "position": 0.0395453064479039,
      "rotation": 0.011050748418524048
    }
  },
  {
    "eposideId": 1,
    "goal": {
      "position": {
        "x": 0.6525146251425512,
        "y": -0.22865024119164712
      },
      "rotation": {
        "theta": 0.5663321799091553
      }
    },
    "finalPose": {
      "position": {
        "x": 0.6718483143235885,
        "y": -0.23452121868326742
      },
      "rotation": {
        "theta": 0.5336689388195219
      }
    },
    "error": {
      "position": 0.020205442683991614,
      "rotation": 0.032663241089633366
    }
  },
  {
    "eposideId": 2,
    "goal": {
      "position": {
        "x": 0.7338054307491593,
        "y": 0.16634039709376197
      },
      "rotation": {
        "theta": -0.6409116865603561
      }
    },
    "finalPose": {
      "position": {
        "x": 0.7319213683411598,
        "y": 0.18336629366024296
      },
      "rotation": {
        "theta": -0.6702958647398884
      }
    },
    "error": {
      "position": 0.01712982326382107,
      "rotation": 0.029384178179532316
    }
  },
  {
    "eposideId": 3,
    "goal": {
      "position": {
        "x": 0.5833174527390893,
        "y": -0.31011635265274046
      },
      "rotation": {
        "theta": 0.11095639761815587
      }
    },
    "finalPose": {
      "position": {
        "x": 0.5674301039518196,
        "y": -0.2800006893809449
      },
      "rotation": {
        "theta": 0.09018705767622484
      }
    },
    "error": {
      "position": 0.03404939097529552,
      "rotation": 0.02076933994193103
    }
  },
  {
    "eposideId": 4,
    "goal": {
      "position": {
        "x": 0.48584156131378936,
        "y": -0.10947164600600422
      },
      "rotation": {
        "theta": 0.036496696747975885
      }
    },
    "finalPose": {
      "position": {
        "x": 0.5063845529079352,
        "y": -0.1454245847429461
      },
      "rotation": {
        "theta": 0.11821338195856447
      }
    },
    "error": {
      "position": 0.04140807055948683,
      "rotation": 0.08171668521058859
    }
  },
  {
    "eposideId": 5,
    "goal": {
      "position": {
        "x": 0.5652217557058241,
        "y": -0.3663418520493904
      },
      "rotation": {
        "theta": -0.08156266135870834
      }
    },
    "finalPose": {
      "position": {
        "x": 0.5840422817939217,
        "y": -0.3366406217569813
      },
      "rotation": {
        "theta": 0.0007663671188215143
      }
    },
    "error": {
      "position": 0.0351621285350515,
      "rotation": 0.08232902847752985
    }
  },
  {
    "eposideId": 6,
    "goal": {
      "position": {
        "x": 0.7259071065184804,
        "y": 0.22573285556615097
      },
      "rotation": {
        "theta": -0.9473609527832523
      }
    },
    "finalPose": {
      "position": {
        "x": 0.6775811679792892,
        "y": 0.2593537904169144
      },
      "rotation": {
        "theta": -0.8662872865606323
      }
    },
    "error": {
      "position": 0.05887073632912167,
      "rotation": 0.08107366622262002
    }
  },
  {
    "eposideId": 7,
    "goal": {
      "position": {
        "x": 0.6948742091043235,
        "y": -0.18949452037431658
      },
      "rotation": {
        "theta": 0.3282391181354385
      }
    },
    "finalPose": {
      "position": {
        "x": 0.7151242657278857,
        "y": -0.19598218310248008
      },
      "rotation": {
        "theta": 0.20170620509973736
      }
    },
    "error": {
      "position": 0.021263926282130394,
      "rotation": 0.12653291303570113
    }
  },
  {
    "eposideId": 8,
    "goal": {
      "position": {
        "x": 0.7664278749597186,
        "y": 0.07065484490190564
      },
      "rotation": {
        "theta": -0.3027861236466262
      }
    },
    "finalPose": {
      "position": {
        "x": 0.7567016506464592,
        "y": 0.04542099778015821
      },
      "rotation": {
        "theta": -0.43946375954510103
      }
    },
    "error": {
      "position": 0.027043418422151445,
      "rotation": 0.13667763589847481
    }
  },
  {
    "eposideId": 9,
    "goal": {
      "position": {
        "x": 0.5712019497996986,
        "y": -0.1592288679480756
      },
      "rotation": {
        "theta": 0.06747418830104862
      }
    },
    "finalPose": {
      "position": {
        "x": 0.5490177255389896,
        "y": -0.2056093599825976
      },
      "rotation": {
        "theta": 0.12501392601042044
      }
    },
    "error": {
      "position": 0.05141293463141147,
      "rotation": 0.05753973770937182
    }
  }
]
